ufc.py
ufc_api-0.0.1.dist-info/LICENSE.txt
ufc_api-0.0.1.dist-info/METADATA
ufc_api-0.0.1.dist-info/WHEEL
ufc_api-0.0.1.dist-info/top_level.txt
ufc_api-0.0.1.dist-info/RECORD
