Metadata-Version: 2.1
Name: ufc-api
Version: 0.0.1
Summary: A web crawler and parser for data on UFC fighters and events
Author-email: Zackary Young <zackyoung454@gmail.com>
Project-URL: Homepage, https://github.com/FritzCapuyan/ufc-api
Classifier: Programming Language :: Python :: 3
Classifier: License :: OSI Approved :: MIT License
Classifier: Operating System :: OS Independent
Requires-Python: >=3.7
License-File: LICENSE.txt
